<?xml version="1.0" encoding="UTF-8"?>
<!DOCTYPE suite SYSTEM "http://testng.org/testng-1.0.dtd">
<suite name="All Test Suite">
    <test verbose="2" preserve-order="true"
          name="/Users/poojauppal/Documents/IntelliJ/RestfulBooker Framework/src/test/java/com/poojauppal/tests/integration/Assignment_TestE2Eflow_05.java">
        <classes>
            <class name="com.poojauppal.tests.integration.Assignment_TestE2Eflow_05">
                <methods>
                    <include name="test_createBooking"/>
                    <include name="test_deleteBooking"/>
                    <include name="test_UpdateBooking"/>
                </methods>
            </class>
        </classes>
    </test>
</suite>